fasthep_flow/__init__.py
fasthep_flow/_version.py
fasthep_flow/_version.pyi
fasthep_flow/cli.py
fasthep_flow/config.py
fasthep_flow/py.typed
fasthep_flow/workflow.py
fasthep_flow/operators/__init__.py
fasthep_flow/operators/base.py
fasthep_flow/operators/bash.py
fasthep_flow-2024.2.1.dist-info/METADATA
fasthep_flow-2024.2.1.dist-info/WHEEL
fasthep_flow-2024.2.1.dist-info/entry_points.txt
fasthep_flow-2024.2.1.dist-info/licenses/LICENSE
fasthep_flow-2024.2.1.dist-info/RECORD
