Metadata-Version: 2.1
Name: fasthep-flow
Version: 2024.2.1
Summary: Convert YAML into a workflow DAG
Project-URL: Homepage, https://github.com/FAST-HEP/fasthep-flow
Project-URL: Bug Tracker, https://github.com/FAST-HEP/fasthep-flow/issues
Project-URL: Discussions, https://github.com/FAST-HEP/fasthep-flow/discussions
Project-URL: Changelog, https://github.com/FAST-HEP/fasthep-flow/releases
Author-email: Luke Kreczko <kreczko@cern.ch>
License-File: LICENSE
Classifier: Development Status :: 2 - Pre-Alpha
Classifier: Intended Audience :: Developers
Classifier: Intended Audience :: Science/Research
Classifier: License :: OSI Approved :: Apache Software License
Classifier: Operating System :: OS Independent
Classifier: Programming Language :: Python
Classifier: Programming Language :: Python :: 3
Classifier: Programming Language :: Python :: 3 :: Only
Classifier: Programming Language :: Python :: 3.10
Classifier: Programming Language :: Python :: 3.11
Classifier: Programming Language :: Python :: 3.12
Classifier: Topic :: Scientific/Engineering
Classifier: Typing :: Typed
Requires-Python: >=3.10
Requires-Dist: eval-type-backport
Requires-Dist: hydra-core
Requires-Dist: omegaconf>=2.1
Requires-Dist: plumbum
Requires-Dist: prefect
Requires-Dist: pyyaml>=5.4
Requires-Dist: typer>=0.4
Requires-Dist: typing-extensions>=3.10
Provides-Extra: dev
Requires-Dist: pytest-cov>=3; extra == 'dev'
Requires-Dist: pytest>=6; extra == 'dev'
Requires-Dist: ruff; extra == 'dev'
Provides-Extra: docs
Requires-Dist: furo>=2023.08.17; extra == 'docs'
Requires-Dist: myst-parser>=0.13; extra == 'docs'
Requires-Dist: sphinx-autodoc-typehints; extra == 'docs'
Requires-Dist: sphinx-copybutton; extra == 'docs'
Requires-Dist: sphinx-inline-tabs; extra == 'docs'
Requires-Dist: sphinx>=7.0; extra == 'docs'
Requires-Dist: sphinxcontrib-mermaid; extra == 'docs'
Provides-Extra: test
Requires-Dist: pytest-cov>=3; extra == 'test'
Requires-Dist: pytest>=6; extra == 'test'
